dark_from_light/__init__.py
dark_from_light/__main__.py
dark_from_light/_cosmo.py
dark_from_light/_data_handling.py
dark_from_light/_group_alloc.py
dark_from_light/_halo_params.py
dark_from_light/_regression.py
dark_from_light/_sampling.py
dark_from_light/run_DfL_ML.py
dark_from_light-0.1.0.dist-info/METADATA
dark_from_light-0.1.0.dist-info/WHEEL
dark_from_light-0.1.0.dist-info/licenses/LICENSE
dark_from_light-0.1.0.dist-info/RECORD
