Metadata-Version: 2.4
Name: dark-from-light
Version: 0.1.0
Summary: A ML-based galaxy group finder and dark matter halo mass estimator for MOONRISE-type data large datasets.
Project-URL: repository, https://github.com/abluck/Dark-from-Light
Author-email: Asa Bluck <abluck@fiu.edu>, Joanna Piotrowska <joannapk@caltech.edu>
License:                                  Apache License
License-File: LICENSE
Keywords: astro-ML,galaxy-groups,group-finder,halo-mass,random-forest
Classifier: Development Status :: 3 - Alpha
Classifier: License :: OSI Approved :: Apache Software License
Classifier: Natural Language :: English
Classifier: Programming Language :: Python :: 3
Requires-Python: >=3.11
Requires-Dist: astropy>=7.0.1
Requires-Dist: jaxtyping>=0.3.2
Requires-Dist: joblib>=1.5.0
Requires-Dist: numpy>=1.26.4
Requires-Dist: scikit-learn==1.5.1
Requires-Dist: tqdm>=4.67.1
